nonebot_plugin_boardgame/__init__.py
nonebot_plugin_boardgame/game.py
nonebot_plugin_boardgame/go.py
nonebot_plugin_boardgame/gomoku.py
nonebot_plugin_boardgame/migrations/dc81a3212383_init_db.py
nonebot_plugin_boardgame/model.py
nonebot_plugin_boardgame/othello.py
nonebot_plugin_boardgame/svg.py
nonebot_plugin_boardgame-0.4.1.dist-info/METADATA
nonebot_plugin_boardgame-0.4.1.dist-info/WHEEL
nonebot_plugin_boardgame-0.4.1.dist-info/RECORD
